{
  "summary": {
    "photo": "IMG_20260505_105451.jpg",
    "node": null,
    "window": null,
    "captured_at": "2026:05:05 10:54:51",
    "width": 4032,
    "height": 2268,
    "exif": {
      "datetime_original": "2026:05:05 10:54:51",
      "camera_make": "HONOR",
      "camera_model": "ALT-NX3",
      "gps_lat": 6.2525358,
      "gps_lon": -75.56826969972222,
      "gps_alt_m": 1502.5
    },
    "counts": {
      "person": 23,
      "bicycle": 0,
      "car": 0,
      "motorcycle": 0,
      "bus": 0,
      "truck": 0,
      "dog": 0,
      "backpack": 1,
      "handbag": 2,
      "suitcase": 0,
      "cell_phone": 0
    },
    "detections": [
      {
        "class_name": "person",
        "confidence": 0.9323632121086121,
        "bbox_xyxy": [
          1426.731689453125,
          1089.340087890625,
          1780.355712890625,
          2020.066650390625
        ]
      },
      {
        "class_name": "person",
        "confidence": 0.9175937175750732,
        "bbox_xyxy": [
          0.5414302349090576,
          1267.7357177734375,
          260.9546813964844,
          1871.7847900390625
        ]
      },
      {
        "class_name": "person",
        "confidence": 0.8518636226654053,
        "bbox_xyxy": [
          3407.654541015625,
          1373.9019775390625,
          3568.376953125,
          1845.033203125
        ]
      },
      {
        "class_name": "person",
        "confidence": 0.8454750180244446,
        "bbox_xyxy": [
          3153.385498046875,
          1331.9501953125,
          3318.59375,
          1809.3359375
        ]
      },
      {
        "class_name": "person",
        "confidence": 0.843770444393158,
        "bbox_xyxy": [
          423.3844299316406,
          1430.858642578125,
          505.60260009765625,
          1598.30810546875
        ]
      },
      {
        "class_name": "person",
        "confidence": 0.8425437211990356,
        "bbox_xyxy": [
          1280.4501953125,
          1398.8427734375,
          1439.204833984375,
          1763.62890625
        ]
      },
      {
        "class_name": "person",
        "confidence": 0.8152965307235718,
        "bbox_xyxy": [
          1023.09033203125,
          1467.8145751953125,
          1064.3167724609375,
          1580.0697021484375
        ]
      },
      {
        "class_name": "person",
        "confidence": 0.7990807890892029,
        "bbox_xyxy": [
          2247.585693359375,
          1483.8052978515625,
          2301.11181640625,
          1598.699951171875
        ]
      },
      {
        "class_name": "person",
        "confidence": 0.7717685699462891,
        "bbox_xyxy": [
          2308.50537109375,
          1473.1162109375,
          2362.28466796875,
          1611.119384765625
        ]
      },
      {
        "class_name": "person",
        "confidence": 0.7708989381790161,
        "bbox_xyxy": [
          2372.093994140625,
          1466.3778076171875,
          2419.70166015625,
          1608.6092529296875
        ]
      },
      {
        "class_name": "person",
        "confidence": 0.7598360776901245,
        "bbox_xyxy": [
          2798.210693359375,
          1452.4852294921875,
          2877.809814453125,
          1567.8466796875
        ]
      },
      {
        "class_name": "person",
        "confidence": 0.7597168684005737,
        "bbox_xyxy": [
          3584.395263671875,
          1572.46337890625,
          3808.854248046875,
          1860.7928466796875
        ]
      },
      {
        "class_name": "person",
        "confidence": 0.7577136754989624,
        "bbox_xyxy": [
          2130.115478515625,
          1481.8192138671875,
          2190.863037109375,
          1634.2445068359375
        ]
      },
      {
        "class_name": "person",
        "confidence": 0.7445803880691528,
        "bbox_xyxy": [
          3561.38623046875,
          1375.3338623046875,
          3703.579345703125,
          1709.405029296875
        ]
      },
      {
        "class_name": "backpack",
        "confidence": 0.7196819186210632,
        "bbox_xyxy": [
          3148.766357421875,
          1400.9537353515625,
          3259.23828125,
          1541.5767822265625
        ]
      },
      {
        "class_name": "person",
        "confidence": 0.7098874449729919,
        "bbox_xyxy": [
          1819.8143310546875,
          1462.2791748046875,
          1870.751953125,
          1595.467041015625
        ]
      },
      {
        "class_name": "person",
        "confidence": 0.7034191489219666,
        "bbox_xyxy": [
          1276.0181884765625,
          1442.191650390625,
          1324.9324951171875,
          1606.150390625
        ]
      },
      {
        "class_name": "handbag",
        "confidence": 0.6774044632911682,
        "bbox_xyxy": [
          1327.0537109375,
          1514.25537109375,
          1410.940185546875,
          1623.4365234375
        ]
      },
      {
        "class_name": "person",
        "confidence": 0.6716899275779724,
        "bbox_xyxy": [
          3046.62890625,
          1494.1517333984375,
          3116.27197265625,
          1588.489501953125
        ]
      },
      {
        "class_name": "handbag",
        "confidence": 0.5121746063232422,
        "bbox_xyxy": [
          3332.531494140625,
          1479.2769775390625,
          3501.345458984375,
          1621.7763671875
        ]
      },
      {
        "class_name": "person",
        "confidence": 0.459021657705307,
        "bbox_xyxy": [
          1295.18017578125,
          1460.738037109375,
          1350.7469482421875,
          1615.5675048828125
        ]
      },
      {
        "class_name": "person",
        "confidence": 0.369938462972641,
        "bbox_xyxy": [
          2122.453857421875,
          1481.9500732421875,
          2151.859130859375,
          1550.1539306640625
        ]
      },
      {
        "class_name": "person",
        "confidence": 0.3619413673877716,
        "bbox_xyxy": [
          2345.971923828125,
          1485.982666015625,
          2374.154296875,
          1606.64013671875
        ]
      },
      {
        "class_name": "person",
        "confidence": 0.35935863852500916,
        "bbox_xyxy": [
          3001.643798828125,
          1502.3248291015625,
          3048.570068359375,
          1606.178466796875
        ]
      },
      {
        "class_name": "person",
        "confidence": 0.3365494906902313,
        "bbox_xyxy": [
          2642.541015625,
          1508.822998046875,
          2676.63134765625,
          1554.1688232421875
        ]
      },
      {
        "class_name": "person",
        "confidence": 0.2552528381347656,
        "bbox_xyxy": [
          7.962009429931641,
          1246.7291259765625,
          150.2856903076172,
          1461.3282470703125
        ]
      }
    ],
    "persons": 23,
    "brightness": 153.13852703504242,
    "contrast": 65.82995868530678,
    "saturation": 61.28388762912572,
    "edge_density": 28.88337250409423,
    "saturation_index": 0.6780289627425043,
    "worker": "worker_photos",
    "yolo_model": "yolo11x.pt",
    "processed_at": "2026-05-07T23:50:09+0000"
  }
}